evaluator/__init__.py
evaluator/commit_evaluator_moderate.py
evaluator/contributtor.py
evaluator/core.py
evaluator/dimensions.py
evaluator/example_moderate_evaluation.py
evaluator/paths.py
evaluator/server.py
evaluator/analyzers/__init__.py
evaluator/analyzers/code_analyzer.py
evaluator/analyzers/collaboration_analyzer.py
evaluator/analyzers/commit_analyzer.py
evaluator/collectors/__init__.py
evaluator/collectors/gitee.py
evaluator/collectors/github.py
evaluator/tools/__init__.py
evaluator/tools/extract_repo_data.py
evaluator/tools/extract_repo_data_api.py
evaluator/tools/extract_repo_data_conservative.py
evaluator/tools/extract_repo_data_moderate.py
oscanner/__init__.py
oscanner/__main__.py
oscanner/cli.py
oscanner/dashboard_dist/404.html
oscanner/dashboard_dist/__next.__PAGE__.txt
oscanner/dashboard_dist/__next._full.txt
oscanner/dashboard_dist/__next._head.txt
oscanner/dashboard_dist/__next._index.txt
oscanner/dashboard_dist/__next._tree.txt
oscanner/dashboard_dist/favicon.ico
oscanner/dashboard_dist/file.svg
oscanner/dashboard_dist/globe.svg
oscanner/dashboard_dist/index.html
oscanner/dashboard_dist/index.txt
oscanner/dashboard_dist/next.svg
oscanner/dashboard_dist/vercel.svg
oscanner/dashboard_dist/window.svg
oscanner/dashboard_dist/404/index.html
oscanner/dashboard_dist/_next/static/QVQeGUDrAaofnvJZhjYVg/_buildManifest.js
oscanner/dashboard_dist/_next/static/QVQeGUDrAaofnvJZhjYVg/_clientMiddlewareManifest.json
oscanner/dashboard_dist/_next/static/QVQeGUDrAaofnvJZhjYVg/_ssgManifest.js
oscanner/dashboard_dist/_next/static/chunks/01095d914547b2b6.js
oscanner/dashboard_dist/_next/static/chunks/17f488d6015676c5.css
oscanner/dashboard_dist/_next/static/chunks/489f88f378ff46fa.js
oscanner/dashboard_dist/_next/static/chunks/60a4be710a3b5153.js
oscanner/dashboard_dist/_next/static/chunks/7340adf74ff47ec0.js
oscanner/dashboard_dist/_next/static/chunks/73469a159b52eb99.js
oscanner/dashboard_dist/_next/static/chunks/7d45b7679d2f78bf.js
oscanner_skill_evaluator-0.1.6.dist-info/licenses/LICENSE
oscanner_skill_evaluator-0.1.6.dist-info/METADATA
oscanner_skill_evaluator-0.1.6.dist-info/WHEEL
oscanner_skill_evaluator-0.1.6.dist-info/entry_points.txt
oscanner_skill_evaluator-0.1.6.dist-info/top_level.txt
oscanner_skill_evaluator-0.1.6.dist-info/RECORD
