Metadata-Version: 2.4
Name: oscanner-skill-evaluator
Version: 0.1.6
Summary: AI-powered engineer capability evaluator (FastAPI backend + optional dashboard)
Author: oscanner contributors
License-Expression: Apache-2.0
Requires-Python: >=3.9
License-File: LICENSE
Requires-Dist: fastapi>=0.109.0
Requires-Dist: uvicorn[standard]>=0.27.0
Requires-Dist: pydantic>=2.5.3
Requires-Dist: requests>=2.31.0
Requires-Dist: httpx>=0.26.0
Requires-Dist: python-dotenv>=1.0.0
Requires-Dist: python-multipart>=0.0.6
Provides-Extra: dev
Requires-Dist: pytest>=8.0.0; extra == "dev"
Requires-Dist: ruff>=0.5.0; extra == "dev"
Dynamic: license-file
